[{"name":"Sagar","location":{"type":"Point","coordinates":[51.5126203,-0.1207112]}},{"name":"Wild Food Cafe","location":{"type":"Point","coordinates":[51.5144744363,-0.1264138965]}},{"name":"Pilpel","location":{"type":"Point","coordinates":[51.5144200989,-0.1072253366]}},{"name":"Dishoom","location":{"type":"Point","coordinates":[51.5123832618,-0.1269489527]}},{"name":"SaladPride","location":{"type":"Point","coordinates":[51.5144414137,-0.1264286041]}},{"name":"La Gelatiera","location":{"type":"Point","coordinates":[51.5110460332,-0.1268280267]}},{"name":"Avobar","location":{"type":"Point","coordinates":[51.5109323962,-0.1241713743]}},{"name":"Farmstand","location":{"type":"Point","coordinates":[51.5144906678,-0.1218344456]}},{"name":"Yorica","location":{"type":"Point","coordinates":[51.5142728089,-0.1346333469]}},{"name":"Abokado","location":{"type":"Point","coordinates":[51.5182763909,-0.1121833102]}},{"name":"Drury 188-189","location":{"type":"Point","coordinates":[51.5160600072,-0.1241107105]}},{"name":"Covent Garden Grind","location":{"type":"Point","coordinates":[51.511005,-0.122526]}},{"name":"Mary Ward Centre Cafe","location":{"type":"Point","coordinates":[51.5211393015,-0.1219259943]}},{"name":"by CHLOE. Covent Garden","location":{"type":"Point","coordinates":[51.5135523552,-0.120382905]}},{"name":"SugarSin","location":{"type":"Point","coordinates":[51.5143173518,-0.1225181426]}},{"name":"Leon","location":{"type":"Point","coordinates":[51.5099888079,-0.1224767237]}},{"name":"Maoz","location":{"type":"Point","coordinates":[51.5128611462,-0.1321998474]}},{"name":"Healthy Olive Tree","location":{"type":"Point","coordinates":[51.5197442002,-0.1089224117]}},{"name":"TY Seven Dials - Timberyard","location":{"type":"Point","coordinates":[51.5128529171,-0.1271978986]}},{"name":"Woodlands Restaurant","location":{"type":"Point","coordinates":[51.5096005476,-0.1317816815]}},{"name":"Pret A Manger","location":{"type":"Point","coordinates":[51.5136287823,-0.1286604122]}},{"name":"Homeslice","location":{"type":"Point","coordinates":[51.5145287497,-0.1264748684]}},{"name":"Caf\u00e9 In The Crypt","location":{"type":"Point","coordinates":[51.5089623036,-0.1267290435]}},{"name":"Apple Butter Cafe","location":{"type":"Point","coordinates":[51.513614,-0.127131]}},{"name":"OXO Tower Brasserie","location":{"type":"Point","coordinates":[51.50838386,-0.10851596]}},{"name":"Govinda's Restaurant","location":{"type":"Point","coordinates":[51.5158970397,-0.1325903449]}},{"name":"Kastner & Ovens","location":{"type":"Point","coordinates":[51.5134441465,-0.1225561494]}},{"name":"Honest Burgers","location":{"type":"Point","coordinates":[51.5053683,-0.1169535]}},{"name":"Horn OK Please","location":{"type":"Point","coordinates":[51.5053576032,-0.1163308389]}},{"name":"Le Pain Quotidien","location":{"type":"Point","coordinates":[51.505478,-0.117289]}},{"name":"Crust Bros Pizza","location":{"type":"Point","coordinates":[51.5027675279,-0.110456866]}},{"name":"wagamama","location":{"type":"Point","coordinates":[51.5058093,-0.1174239]}},{"name":"The Diner","location":{"type":"Point","coordinates":[51.5103038616,-0.121936168]}},{"name":"Redemption","location":{"type":"Point","coordinates":[51.51444,-0.12639105]}},{"name":"The Travel Caf\u00e9","location":{"type":"Point","coordinates":[51.4997053933,-0.1141358292]}},{"name":"Ceviche Soho","location":{"type":"Point","coordinates":[51.5137,-0.131546]}},{"name":"Crosstown Doughnuts & Coffee","location":{"type":"Point","coordinates":[51.5140425663,-0.1346042714]}},{"name":"Shake Shack Covent Garden","location":{"type":"Point","coordinates":[51.5118164319,-0.1225980757]}},{"name":"Abokado","location":{"type":"Point","coordinates":[51.5196021574,-0.1119949939]}},{"name":"The National Caf\u00e9","location":{"type":"Point","coordinates":[51.5088025569,-0.1275444031]}},{"name":"L'ETO Caff\u00e8","location":{"type":"Point","coordinates":[51.5143444465,-0.1346694799]}},{"name":"Flat White","location":{"type":"Point","coordinates":[51.5135465062,-0.1349784623]}},{"name":"Carpo Piccadilly","location":{"type":"Point","coordinates":[51.5095638594,-0.1355359952]}},{"name":"Kricket","location":{"type":"Point","coordinates":[51.5107270792,-0.1352437351]}},{"name":"Wahaca","location":{"type":"Point","coordinates":[51.5067503588,-0.1161256864]}},{"name":"Sartori","location":{"type":"Point","coordinates":[51.511784,-0.128021]}},{"name":"The Table Caf\u00e9","location":{"type":"Point","coordinates":[51.5055,-0.09994514]}},{"name":"Sagar Vegetarian","location":{"type":"Point","coordinates":[51.518512,-0.132796]}},{"name":"Soho's Secret Tea Room","location":{"type":"Point","coordinates":[51.513179319,-0.1301872043]}},{"name":"Fitology Kitchen","location":{"type":"Point","coordinates":[51.5074679142,-0.1100850104]}},{"name":"Waterstones","location":{"type":"Point","coordinates":[51.5176993679,-0.1313909375]}},{"name":"Soho House (Roof Deck)","location":{"type":"Point","coordinates":[51.5132964549,-0.1308771212]}},{"name":"Honest Burgers","location":{"type":"Point","coordinates":[51.5134184064,-0.1328838857]}},{"name":"Janetira Thai","location":{"type":"Point","coordinates":[51.5121051511,-0.1344959337]}},{"name":"Margot","location":{"type":"Point","coordinates":[51.5148135453,-0.1218517838]}},{"name":"Veeraswamy","location":{"type":"Point","coordinates":[51.5101570037,-0.1377305203]}},{"name":"Woolleys","location":{"type":"Point","coordinates":[51.520325637,-0.1180017936]}},{"name":"Vantra Loungevity","location":{"type":"Point","coordinates":[51.510611,-0.131857]}},{"name":"Coleman Coffee Roasters","location":{"type":"Point","coordinates":[51.500636,-0.112947]}},{"name":"Whole Foods Market","location":{"type":"Point","coordinates":[51.5104875094,-0.1359068923]}},{"name":"Tokyo Diner","location":{"type":"Point","coordinates":[51.5118316048,-0.1294159349]}},{"name":"Dirty Bones","location":{"type":"Point","coordinates":[51.5106975094,-0.1353722847]}},{"name":"The Barbary","location":{"type":"Point","coordinates":[51.5144455494,-0.1263704889]}},{"name":"Pho Covent Garden","location":{"type":"Point","coordinates":[51.5139659726,-0.1227612492]}},{"name":"Catalyst Cafe","location":{"type":"Point","coordinates":[51.5197045032,-0.1120515854]}},{"name":"Prufrock Coffee","location":{"type":"Point","coordinates":[51.51992634,-0.10945263]}},{"name":"Ole & Steen","location":{"type":"Point","coordinates":[51.5091959,-0.1327875]}},{"name":"Lyceum Tavern","location":{"type":"Point","coordinates":[51.5112087289,-0.1195042857]}},{"name":"Vital Ingredient","location":{"type":"Point","coordinates":[51.5142381682,-0.1095014233]}},{"name":"Pizza Pilgrims","location":{"type":"Point","coordinates":[51.5149060663,-0.1333095565]}},{"name":"Patara","location":{"type":"Point","coordinates":[51.514135887,-0.1308551163]}},{"name":"balance","location":{"type":"Point","coordinates":[51.5014055005,-0.1111793786]}},{"name":"Chipotle Mexican Grill","location":{"type":"Point","coordinates":[51.51468,-0.12957]}},{"name":"The Espresso Room","location":{"type":"Point","coordinates":[51.51839931,-0.1208240232]}},{"name":"GAIL's Bakery","location":{"type":"Point","coordinates":[51.5186527053,-0.1319992407]}},{"name":"East Street","location":{"type":"Point","coordinates":[51.5165403016,-0.1331467966]}},{"name":"Jack's","location":{"type":"Point","coordinates":[51.5042979242,-0.1058408944]}},{"name":"Bella Italia","location":{"type":"Point","coordinates":[51.5111833307,-0.1295749301]}},{"name":"Paul A Young Fine Chocolates","location":{"type":"Point","coordinates":[51.514114,-0.13463348]}},{"name":"Soho Vegan Market","location":{"type":"Point","coordinates":[51.512285,-0.133766]}},{"name":"PizzaExpress","location":{"type":"Point","coordinates":[51.5114504175,-0.1272678045]}},{"name":"Shake Shack Leicester Square","location":{"type":"Point","coordinates":[51.510498,-0.1316948]}},{"name":"Hipchips","location":{"type":"Point","coordinates":[51.5127098242,-0.132428905]}},{"name":"Wahaca","location":{"type":"Point","coordinates":[51.5027358,-0.1100846]}},{"name":"Abokado","location":{"type":"Point","coordinates":[51.5199896055,-0.1190451703]}},{"name":"Benito's Hat","location":{"type":"Point","coordinates":[51.5111332502,-0.1259237925]}},{"name":"GAIL's Bakery","location":{"type":"Point","coordinates":[51.514232421,-0.1345499197]}},{"name":"Abokado","location":{"type":"Point","coordinates":[51.5141539741,-0.1029042384]}},{"name":"Rossopomodoro","location":{"type":"Point","coordinates":[51.5129660514,-0.127190482]}},{"name":"Pizza Express","location":{"type":"Point","coordinates":[51.5151235579,-0.1333170794]}},{"name":"Abokado","location":{"type":"Point","coordinates":[51.5192609051,-0.1087096595]}},{"name":"Banana Tree","location":{"type":"Point","coordinates":[51.5131224325,-0.1337486625]}},{"name":"Pret A Manger","location":{"type":"Point","coordinates":[51.5031287861,-0.112521644]}},{"name":"Misato","location":{"type":"Point","coordinates":[51.5108955724,-0.1316538958]}},{"name":"The Delhi Brasserie","location":{"type":"Point","coordinates":[51.5133155899,-0.1312796212]}},{"name":"Taro","location":{"type":"Point","coordinates":[51.5114434583,-0.1355856657]}},{"name":"Chin Chin Club","location":{"type":"Point","coordinates":[51.514322037,-0.1311134184]}},{"name":"Natural Kitchen","location":{"type":"Point","coordinates":[51.5030575659,-0.1119391878]}},{"name":"Bao","location":{"type":"Point","coordinates":[51.5189847093,-0.1337778568]}},{"name":"Ev Restaurant","location":{"type":"Point","coordinates":[51.5042852272,-0.1061917199]}}]