[{"name":"Vinnie's Pizzeria","location":{"type":"Point","coordinates":[40.7259255669,-73.9417111392]}},{"name":"Jungle Cafe","location":{"type":"Point","coordinates":[40.730201,-73.954761]}},{"name":"Paulie Gee\u2019s","location":{"type":"Point","coordinates":[40.729801247,-73.9585204635]}},{"name":"Adelina's","location":{"type":"Point","coordinates":[40.7303013011,-73.9533519329]}},{"name":"Vinnie's Pizzeria","location":{"type":"Point","coordinates":[40.7188494756,-73.9566431645]}},{"name":"Brooklyn Whiskers","location":{"type":"Point","coordinates":[40.737482,-73.954402]}},{"name":"Screamer's Pizzeria","location":{"type":"Point","coordinates":[40.7235582742,-73.95070984]}},{"name":"Champs Diner","location":{"type":"Point","coordinates":[40.7083345452,-73.9408161065]}},{"name":"Xilonen","location":{"type":"Point","coordinates":[40.723491,-73.951925]}},{"name":"Hana Food","location":{"type":"Point","coordinates":[40.7139895852,-73.9511712604]}},{"name":"Modern Love Brooklyn","location":{"type":"Point","coordinates":[40.709911053,-73.9510079946]}},{"name":"Happy Zoe Vegan Bakery","location":{"type":"Point","coordinates":[40.719246,-73.944252]}},{"name":"Bunna Cafe","location":{"type":"Point","coordinates":[40.7050118982,-73.9280679301]}},{"name":"JuiceryKitchen","location":{"type":"Point","coordinates":[40.717929781,-73.9521887318]}},{"name":"by CHLOE.","location":{"type":"Point","coordinates":[40.7152143,-73.9593632]}},{"name":"Little Choc Apothecary","location":{"type":"Point","coordinates":[40.7119557279,-73.957333436]}},{"name":"Azure Natural & Organic Foods","location":{"type":"Point","coordinates":[40.7076437535,-73.9416040761]}},{"name":"Bar Velo Brooklyn","location":{"type":"Point","coordinates":[40.7070966017,-73.9543318189]}},{"name":"I Am Thai Restaurant","location":{"type":"Point","coordinates":[40.7445497964,-73.9151956561]}},{"name":"sweetgreen","location":{"type":"Point","coordinates":[40.7157953,-73.9591804]}},{"name":"Loving Hut","location":{"type":"Point","coordinates":[40.7125489425,-73.9411059872]}},{"name":"The Butcher\u2019s Daughter","location":{"type":"Point","coordinates":[40.714905,-73.95852]}},{"name":"Brooklyn Standard","location":{"type":"Point","coordinates":[40.725385,-73.945652]}},{"name":"The Shanti Shack","location":{"type":"Point","coordinates":[40.7168932492,-73.962378034]}},{"name":"Paulie Gee's Slice Shop","location":{"type":"Point","coordinates":[40.7284441599,-73.9573406877]}},{"name":"Vegan Shop Up","location":{"type":"Point","coordinates":[40.7054560397,-73.9328743993]}},{"name":"Dig Inn","location":{"type":"Point","coordinates":[40.7156985,-73.9590152]}},{"name":"Terms Of Endearment","location":{"type":"Point","coordinates":[40.716221,-73.962272]}},{"name":"juice press","location":{"type":"Point","coordinates":[40.7187666322,-73.9578568333]}},{"name":"Chickpea & Olive","location":{"type":"Point","coordinates":[40.7201080322,-73.9624328613]}},{"name":"Ovenly","location":{"type":"Point","coordinates":[40.7297076828,-73.9595444846]}},{"name":"Pine Box Rock Shop","location":{"type":"Point","coordinates":[40.7053749967,-73.9326912352]}},{"name":"Hartbreakers","location":{"type":"Point","coordinates":[40.701627,-73.922853]}},{"name":"Eat","location":{"type":"Point","coordinates":[40.7274132481,-73.9515388012]}},{"name":"Eagle Trading Co.","location":{"type":"Point","coordinates":[40.734954,-73.95824]}},{"name":"Sweetleaf","location":{"type":"Point","coordinates":[40.743294,-73.95159]}},{"name":"De Mole","location":{"type":"Point","coordinates":[40.7393198198,-73.9204139109]}},{"name":"Franchia","location":{"type":"Point","coordinates":[40.7475490451,-73.9811238022]}},{"name":"Kajitsu","location":{"type":"Point","coordinates":[40.7497628397,-73.9776876903]}},{"name":"Jujube Tree","location":{"type":"Point","coordinates":[40.7653089306,-73.9181615171]}},{"name":"The Blue Stove","location":{"type":"Point","coordinates":[40.7175123227,-73.9449076866]}},{"name":"Dr. Cow Storefront","location":{"type":"Point","coordinates":[40.7109440392,-73.9648233306]}},{"name":"Williamsburg Pizza","location":{"type":"Point","coordinates":[40.708302614,-73.9506986311]}},{"name":"Two Boots Williamsburg","location":{"type":"Point","coordinates":[40.7169856689,-73.9565630516]}},{"name":"sweetgreen","location":{"type":"Point","coordinates":[40.7442426,-73.9729059]}},{"name":"Le Botaniste","location":{"type":"Point","coordinates":[40.751316,-73.974187]}},{"name":"Jajaja Plantas Mexicana","location":{"type":"Point","coordinates":[40.7168953287,-73.9618622338]}},{"name":"Aubergine Cafe","location":{"type":"Point","coordinates":[40.7460159948,-73.9142357272]}},{"name":"House of Small Wonder","location":{"type":"Point","coordinates":[40.7188649941,-73.9608728448]}},{"name":"Juice Generation","location":{"type":"Point","coordinates":[40.7514123373,-73.9765369892]}},{"name":"Sol Sips","location":{"type":"Point","coordinates":[40.699135,-73.92251]}},{"name":"C. Lo Cafe","location":{"type":"Point","coordinates":[40.70634,-73.905525]}},{"name":"Marty's V Burger","location":{"type":"Point","coordinates":[40.7419704173,-73.9827095809]}},{"name":"Chennai Garden by Tiffin Wallah","location":{"type":"Point","coordinates":[40.7428257406,-73.982834855]}},{"name":"Wild Ginger Pan-Asian Vegan Cuisine","location":{"type":"Point","coordinates":[40.7189860419,-73.9552670326]}},{"name":"Swallow Caf\u00e9","location":{"type":"Point","coordinates":[40.7053849971,-73.9333278741]}},{"name":"Martha's Country Bakery","location":{"type":"Point","coordinates":[40.7149176577,-73.9607896635]}},{"name":"Momo Sushi Shack","location":{"type":"Point","coordinates":[40.7051164788,-73.9333025293]}},{"name":"Natural Frontier Market","location":{"type":"Point","coordinates":[40.7397231881,-73.9825571821]}},{"name":"Saint Vitus Bar","location":{"type":"Point","coordinates":[40.7367075495,-73.9551058704]}},{"name":"K\u00e1v\u00e9 Espresso Bar","location":{"type":"Point","coordinates":[40.704876,-73.928785]}},{"name":"Cafe Spice","location":{"type":"Point","coordinates":[40.7525420403,-73.9773813588]}},{"name":"Maoz Vegan","location":{"type":"Point","coordinates":[40.751706,-73.974375]}},{"name":"Acai Berry","location":{"type":"Point","coordinates":[40.7242807409,-73.9511101009]}},{"name":"Sotto Le Stelle","location":{"type":"Point","coordinates":[40.74342434,-73.9201652047]}},{"name":"Mulberry & Vine","location":{"type":"Point","coordinates":[40.7521339696,-73.974010028]}},{"name":"Amituofo","location":{"type":"Point","coordinates":[40.7038422646,-73.9328298973]}},{"name":"The Meatball Shop","location":{"type":"Point","coordinates":[40.7181703162,-73.9575015442]}},{"name":"M Noodle Shop","location":{"type":"Point","coordinates":[40.7141168143,-73.9506861926]}},{"name":"Sensible Edibles","location":{"type":"Point","coordinates":[40.7420834755,-73.9349287216]}},{"name":"Maguro Sushi","location":{"type":"Point","coordinates":[40.7421755735,-73.981259837]}},{"name":"Happy Zoe Vegan Bakery","location":{"type":"Point","coordinates":[40.724038,-73.949593]}},{"name":"Earth","location":{"type":"Point","coordinates":[40.7168067541,-73.944899845]}},{"name":"Brooklyn's Natural","location":{"type":"Point","coordinates":[40.7054839464,-73.9333502061]}},{"name":"The Wheelhouse","location":{"type":"Point","coordinates":[40.6999969844,-73.9244007012]}},{"name":"Bozu","location":{"type":"Point","coordinates":[40.7129762657,-73.9574779035]}},{"name":"Just Salad","location":{"type":"Point","coordinates":[40.7493324434,-73.9756603384]}},{"name":"Madame Sousou Cafe","location":{"type":"Point","coordinates":[40.763155,-73.922061]}},{"name":"Maison Thai","location":{"type":"Point","coordinates":[40.7449691774,-73.9757696177]}},{"name":"The Sandwich Shop","location":{"type":"Point","coordinates":[40.71154,-73.946273]}},{"name":"Cardamom","location":{"type":"Point","coordinates":[40.743842,-73.921248]}},{"name":"A.T.M. Vegan Deli","location":{"type":"Point","coordinates":[40.721799,-73.95839]}},{"name":"Applegate Kitchens","location":{"type":"Point","coordinates":[40.7523143925,-73.9720141501]}},{"name":"Martha's Country Bakery","location":{"type":"Point","coordinates":[40.7180797532,-73.9574373329]}},{"name":"Milkflower","location":{"type":"Point","coordinates":[40.7630365221,-73.920705125]}},{"name":"Whole Bowl","location":{"type":"Point","coordinates":[40.713985,-73.95234]}},{"name":"Tofubox","location":{"type":"Point","coordinates":[40.711254,-73.94679]}},{"name":"Oslo Coffee Roasters","location":{"type":"Point","coordinates":[40.7131048872,-73.9621786703]}},{"name":"Oregano","location":{"type":"Point","coordinates":[40.7190384242,-73.958557187]}},{"name":"Bhatti Indian Grill","location":{"type":"Point","coordinates":[40.7420650243,-73.9829834361]}},{"name":"Chickpea & Olive","location":{"type":"Point","coordinates":[40.71616,-73.95953]}},{"name":"983 Bushwick's Living Room","location":{"type":"Point","coordinates":[40.7029464349,-73.933351611]}},{"name":"Ange Noir Cafe","location":{"type":"Point","coordinates":[40.7041189964,-73.9340960001]}},{"name":"Rizzo's Fine Pizza","location":{"type":"Point","coordinates":[40.7634567844,-73.9152712899]}},{"name":"Minca","location":{"type":"Point","coordinates":[40.7241753311,-73.9828167726]}},{"name":"Blue Collar","location":{"type":"Point","coordinates":[40.711357718,-73.9577184776]}},{"name":"LIC CSA","location":{"type":"Point","coordinates":[40.7559697428,-73.9283323288]}},{"name":"Le Pain Quotidien","location":{"type":"Point","coordinates":[40.752260652,-73.973633498]}},{"name":"Oasis","location":{"type":"Point","coordinates":[40.7176678262,-73.9575484457]}},{"name":"Westville East","location":{"type":"Point","coordinates":[40.728427623,-73.9818936364]}}]